LICENSE
README.md
pyproject.toml
wsidata/__init__.py
wsidata/_const.py
wsidata/_logging.py
wsidata/_normalizer.py
wsidata/_utils.py
wsidata/_version.py
wsidata/py.typed
wsidata/_model/__init__.py
wsidata/_model/core.py
wsidata/accessors/__init__.py
wsidata/accessors/dataset.py
wsidata/accessors/fetch.py
wsidata/accessors/iter.py
wsidata/accessors/register.py
wsidata/dataset/__init__.py
wsidata/dataset/disk.py
wsidata/dataset/feature.py
wsidata/dataset/graph.py
wsidata/dataset/image.py
wsidata/dataset/multislides/__init__.py
wsidata/dataset/multislides/builder.py
wsidata/dataset/multislides/dataset.py
wsidata/dataset/multislides/sampler.py
wsidata/io/__init__.py
wsidata/io/_elems.py
wsidata/io/_wsi.py
wsidata/reader/__init__.py
wsidata/reader/_reader_datatree_zarr_v2.py
wsidata/reader/_reader_datatree_zarr_v3.py
wsidata/reader/base.py
wsidata/reader/bioformats.py
wsidata/reader/cucim.py
wsidata/reader/openslide.py
wsidata/reader/spatialdata_image2d.py
wsidata/reader/tiffslide.py
wsidata/reader/utils.py
wsidata-0.8.0.dist-info/METADATA
wsidata-0.8.0.dist-info/WHEEL
wsidata-0.8.0.dist-info/licenses/LICENSE
wsidata-0.8.0.dist-info/RECORD
