Metadata-Version: 2.4
Name: wsidata
Version: 0.8.0
Summary: Efficient data structures and IO for whole slide image analysis
Author-email: Yimin Zheng <yzheng@cemm.at>, Ernesto Abila <eabila@cemm.at>, "André F. Rendeiro" <arendeiro@cemm.at>
License-Expression: MIT
License-File: LICENSE
Keywords: data structure,histopathology,image analysis,whole slide image
Classifier: Development Status :: 3 - Alpha
Classifier: Intended Audience :: Science/Research
Classifier: License :: OSI Approved :: MIT License
Classifier: Natural Language :: English
Classifier: Operating System :: OS Independent
Classifier: Programming Language :: Python :: 3
Classifier: Topic :: File Formats
Classifier: Topic :: Scientific/Engineering :: Bio-Informatics
Requires-Python: >=3.11
Requires-Dist: opencv-python-headless
Requires-Dist: openslide-bin>=4.0.0.2
Requires-Dist: openslide-python>=1.4.1
Requires-Dist: rich
Requires-Dist: spatialdata>=0.5.0
Requires-Dist: tiffslide
Requires-Dist: torch>=2.0.0
Provides-Extra: bioformats
Requires-Dist: scyjava; extra == 'bioformats'
Provides-Extra: cucim
Requires-Dist: cucim; extra == 'cucim'
Provides-Extra: plot
Requires-Dist: legendkit; extra == 'plot'
Requires-Dist: matplotlib; extra == 'plot'
Provides-Extra: stain
Requires-Dist: torchstain; extra == 'stain'
